udocker/__init__.py
udocker/cli.py
udocker/cmdparser.py
udocker/commonlocalfile.py
udocker/config.py
udocker/docker.py
udocker/genstr.py
udocker/localfile.py
udocker/maincmd.py
udocker/msg.py
udocker/oci.py
udocker/tools.py
udocker/umain.py
udocker/container/__init__.py
udocker/container/localrepo.py
udocker/container/structure.py
udocker/engine/__init__.py
udocker/engine/base.py
udocker/engine/execmode.py
udocker/engine/fakechroot.py
udocker/engine/nvidia.py
udocker/engine/proot.py
udocker/engine/runc.py
udocker/engine/singularity.py
udocker/etc/udocker.conf
udocker/helper/__init__.py
udocker/helper/archinfo.py
udocker/helper/elfpatcher.py
udocker/helper/hostinfo.py
udocker/helper/keystore.py
udocker/helper/nixauth.py
udocker/helper/osinfo.py
udocker/helper/unique.py
udocker/helper/unshare.py
udocker/utils/__init__.py
udocker/utils/chksum.py
udocker/utils/curl.py
udocker/utils/filebind.py
udocker/utils/fileutil.py
udocker/utils/mountpoint.py
udocker/utils/uenv.py
udocker/utils/uprocess.py
udocker/utils/uvolume.py
udocker-1.3.17.dist-info/AUTHORS.md
udocker-1.3.17.dist-info/LICENSE
udocker-1.3.17.dist-info/METADATA
udocker-1.3.17.dist-info/WHEEL
udocker-1.3.17.dist-info/entry_points.txt
udocker-1.3.17.dist-info/top_level.txt
udocker-1.3.17.dist-info/RECORD
