Metadata-Version: 2.1
Name: udocker
Version: 1.3.17
Summary: A basic user tool to execute simple docker         containers in batch or interactive systems without root privileges
Home-page: https://github.com/indigo-dc/udocker
Author: Jorge Gomes
Author-email: udocker@lip.pt
License: Apache Software License 2.0
Keywords: Linux containers,HPC on cloud,Virtualization
Platform: UNKNOWN
Classifier: Development Status :: 5 - Production/Stable
Classifier: Intended Audience :: Developers
Classifier: Intended Audience :: End Users/Desktop
Classifier: Intended Audience :: Science/Research
Classifier: License :: OSI Approved :: Apache Software License
Classifier: Natural Language :: English
Classifier: Programming Language :: Python :: 2
Classifier: Programming Language :: Python :: 2.7
Classifier: Programming Language :: Python :: 3
Classifier: Programming Language :: Python :: 3.6
Classifier: Programming Language :: Python :: 3.7
Classifier: Programming Language :: Python :: 3.8
Classifier: Programming Language :: Python :: 3.9
Classifier: Programming Language :: Python :: 3.10
Classifier: Programming Language :: Python :: 3.11
Classifier: Topic :: System
Classifier: Topic :: Utilities
License-File: LICENSE
License-File: AUTHORS.md
